<?xml version="1.0"?>
<arts format="ascii" version="1">
<GriddedField3>
<Vector name="Pressure" nelem="46">
              110000
              101300
               90400
               80500
               71500
               63300
               55900
               49200
               43200
               37800
               32900
               28600
               24700
               21300
               18200
               15600
               13200
               11100
                9370
                7890
                6660
                5650
                4800
                4090
                3500
                3000
                2570
                1763
                1220
                 852
                 600
                 426
                 305
                 220
                 159
                 116
   85.40000000000001
                45.6
                23.9
                12.1
                 5.8
                 2.6
                 1.1
                0.44
               0.172
 0.06900000000000001
</Vector>
<Vector name="Latitude" nelem="1">
                   0
</Vector>
<Vector name="Longitude" nelem="1">
                   0
</Vector>
<Tensor3 name="VMR" npages="46" nrows="1" ncols="1">
1.701342e-06
1.701342e-06
1.701444e-06
1.701416e-06
1.701587e-06
1.700802e-06
1.701112e-06
1.701404e-06
1.699453e-06
1.698690e-06
1.693960e-06
1.686472e-06
1.675959e-06
1.662474e-06
1.646219e-06
1.627326e-06
1.606313e-06
1.583224e-06
1.554057e-06
1.522355e-06
1.480863e-06
1.424933e-06
1.355778e-06
1.272851e-06
1.191599e-06
1.118794e-06
1.055750e-06
9.877229e-07
9.143622e-07
8.304962e-07
7.468172e-07
6.625289e-07
5.642210e-07
4.616925e-07
3.633099e-07
2.775410e-07
2.101659e-07
1.652494e-07
1.501634e-07
1.501042e-07
1.500754e-07
1.501361e-07
1.500998e-07
1.501587e-07
1.400945e-07
1.297393e-07
</Tensor3>
</GriddedField3>
</arts>
